README.md
setup.py
goflow/__init__.py
goflow.egg-info/PKG-INFO
goflow.egg-info/SOURCES.txt
goflow.egg-info/dependency_links.txt
goflow.egg-info/top_level.txt
goflow/adapter/__init__.py
goflow/adapter/init_ivp.py
goflow/models/__init__.py
goflow/models/base.py
goflow/models/binder.py
goflow/models/bohn.py
goflow/models/corson.py
goflow/models/kramer.py
goflow/models/meigel.py
goflow/models/murray.py