Metadata-Version: 2.1
Name: goflow
Version: 0.1.2
Summary: Collection of tools for computation of flows and and fluxes on Kirchhoff circuits and their corresponding adaptation. 
Home-page: https://github.com/felixk1990/go-with-the-flow
Author: felixk1990
Author-email: felixuwekramer@protonmail.com
License: UNKNOWN
Platform: UNKNOWN
Classifier: Programming Language :: Python :: 3
Classifier: License :: OSI Approved :: MIT License
Classifier: Operating System :: OS Independent
Requires-Python: >=3.6
